cdt_path/__init__.py
cdt_path/demo.py
cdt_path/utils.py
cdt_path/baseDCEL/__init__.py
cdt_path/baseDCEL/definition.py
cdt_path/baseDCEL/test.py
cdt_path/baseDCEL/test2.py
cdt_path/circumcircle/__init__.py
cdt_path/circumcircle/calculate.py
cdt_path/constrained_delaunay/__init__.py
cdt_path/constrained_delaunay/cdt_edge_additions.py
cdt_path/constrained_delaunay/definition.py
cdt_path/convex_hull/__init__.py
cdt_path/convex_hull/display.py
cdt_path/convex_hull/divide_and_conquer.py
cdt_path/convex_hull/extreme_edge.py
cdt_path/convex_hull/gift_wrap.py
cdt_path/convex_hull/incremental.py
cdt_path/convex_hull/quick_hull.py
cdt_path/delaunay/__init__.py
cdt_path/delaunay/definition.py
cdt_path/delaunay/definition_Old_2.py
cdt_path/delaunay/hhh.py
cdt_path/delaunay/incremental.py
cdt_path/delaunay/incremental_Old.py
cdt_path/demo/Interact_part.py
cdt_path/demo/__init__.py
cdt_path/file/__init__.py
cdt_path/file/load.py
cdt_path/interact/__init__.py
cdt_path/interact/base.py
cdt_path/interact/border.py
cdt_path/interact/draw.py
cdt_path/interact/utils.py
cdt_path/manipulate/__init__.py
cdt_path/manipulate/circumcircle.py
cdt_path/manipulate/combine.py
cdt_path/manipulate/load.py
cdt_path/manipulate/save.py
cdt_path/pathplan/A_star.py
cdt_path/pathplan/A_star_O.py
cdt_path/pathplan/__init__.py
cdt_path/pathplan/funnel - 副本.py
cdt_path/pathplan/funnel.py
cdt_path/pathplan/utils.py
cdt_path-2.3.0.dist-info/METADATA
cdt_path-2.3.0.dist-info/WHEEL
cdt_path-2.3.0.dist-info/top_level.txt
cdt_path-2.3.0.dist-info/RECORD
