Metadata-Version: 2.1
Name: cdt-path
Version: 2.3.0
Summary: Constrainted Delaunay Triangle for path-planning
Author: CaiShu
Author-email: caiyi@mail.ustc.edu.cn
Classifier: Programming Language :: Python :: 3
Classifier: Programming Language :: Python :: Implementation :: CPython
Requires-Dist: matplotlib
Requires-Dist: triangle
